poetry_demo_datasketch/__init__.py
poetry_demo_datasketch/demo.py
poetry_demo_test_datasketch-0.1.0.dist-info/METADATA
poetry_demo_test_datasketch-0.1.0.dist-info/WHEEL
poetry_demo_test_datasketch-0.1.0.dist-info/RECORD
