Metadata-Version: 2.1
Name: poetry-demo-test-datasketch
Version: 0.1.0
Summary: 
Author: Your Name
Author-email: you@example.com
Requires-Python: >=3.11,<4.0
Classifier: Programming Language :: Python :: 3
Classifier: Programming Language :: Python :: 3.11
Requires-Dist: pendulum (>=3.0.0,<4.0.0)
